{
  "hero": {
    "h1": "Our Fleet",
    "p": "From comfortable minibuses for intimate group outings to spacious coaches for larger events, each vehicle is equipped with modern amenities to ensure a smooth and enjoyable ride. No matter the occasion, our fleet is ready to take you wherever you need to go!",
    "buttons": {
      "primary": {
        "text": "Explore vehicles",
        "link": "#vehicles"
      },
      "secondary": {
        "text": "Travel Safety",
        "link": "#safety"
      }
    },
    "video": {
      "src": "/assets/video/ev-tours-charter-fleet.mp4",
      "poster": "/assets/video/ev-tours-charter-fleet.jpg",
      "fallback": "/assets/video/ev-tours-charter-fleet.jpg"
    }
  },
  "vehicles": {
    "heading": "Vehicles",
    "subheading": "Our diverse and well-maintained fleet of vehicles is designed to meet all your transport needs."
  },
  "buses": [
    {
      "model": "Van",
      "capacity": "11-12",
      "features": [
        { "icon": "seatbelt", "text": "Seatbelts" },
        { "icon": "snowflake", "text": "Air conditioning" },
        { "icon": "temperature-half", "text": "Heating" },
        { "icon": "bluetooth", "text": "Bluetooth" },
        { "icon": "music", "text": "AUX Connection" }
      ],
      "exterior-image": {
        "src": "/assets/img/van-exterior.jpg",
        "alt": "Exterior of the van"
      },
      "interior-image": {
        "src": "/assets/img/van-interior.webp",
        "alt": "Interior of the van"
      }
    },
    {
      "model": "Mini Bus",
      "capacity": "24",
      "features": [
        { "icon": "seatbelt", "text": "Seatbelts" },
        { "icon": "snowflake", "text": "Air conditioning" },
        { "icon": "temperature-half", "text": "Heating" },
        { "icon": "bluetooth", "text": "Bluetooth" }
      ],
      "exterior-image": {
        "src": "/assets/img/minibus-exterior.webp",
        "alt": "Exterior of the  minibus"
      },
      "interior-image": {
        "src": "/assets/img/minibus-interior.webp",
        "alt": "Interior of the minibus"
      }
    },
    {
      "model": "Low Floor",
      "capacity": "43",
      "features": [
        { "icon": "snowflake", "text": "Air conditioning" },
        { "icon": "temperature-half", "text": "Heating" },
        { "icon": "bluetooth", "text": "Bluetooth" },
        { "icon": "wheelchair", "text": "Ramp access" }
      ],
      "exterior-image": {
        "src": "/assets/img/low-floor-exterior.webp",
        "alt": "Exterior of the low floor bus"
      },
      "interior-image": {
        "src": "/assets/img/low-floor-interior.webp",
        "alt": "Interior of the low floor bus"
      }
    },
    {
      "model": "Coach",
      "capacity": "57",
      "features": [
        { "icon": "seatbelt", "text": "Seatbelts" },
        { "icon": "snowflake", "text": "Air conditioning" },
        { "icon": "temperature-half", "text": "Heating" },
        { "icon": "bluetooth", "text": "Bluetooth" },
        { "icon": "battery-full", "text": "Phone chargers" },
        { "icon": "suitcase-rolling", "text": "Storage space" },
        { "icon": "tv", "text": "Television" }
      ],
      "exterior-image": {
        "src": "/assets/img/coach-exterior.webp",
        "alt": "Exterior of the coach"
      },
      "interior-image": {
        "src": "/assets/img/coach-interior.webp",
        "alt": "Interior of the coach"
      }
    }
  ],
  "safety": {
    "heading": "Your safety is our top priority",
    "text": "We understand that safety is a crucial aspect of your travel experience. That’s why we implement strict safety measures and protocols to ensure that every journey is secure and worry-free.",
    "sections": [
      {
        "icon": "wrench",
        "heading": "Vehicle maintenance",
        "text": [
          "Each vehicle undergoes regular inspections and maintenance to ensure it meets our high safety standards.",
          "We keep our buses in peak condition to prevent issues and ensure a smooth ride for all passengers."
        ]
      },
      {
        "icon": "id-card",
        "heading": "Trained drivers",
        "text": [
          "All our drivers are thoroughly trained and vetted to provide you with a safe travel experience.",
          "They are not only skilled behind the wheel but also knowledgeable about the routes and best practices for passenger safety."
        ]
      },
      {
        "icon": "shield-halved",
        "heading": "Saftey protocols",
        "text": [
          "Our comprehensive safety protocols include regular safety briefings for our drivers and GPS tracking of our fleet.",
          "From seatbelt use to emergency procedures, every aspect of your journey is covered so you can relax and enjoy the ride."
        ]
      }
    ]
  },
  "cta": {
    "heading": "Ready to choose your ride?",
    "text": [
      "Explore our fleet and find the perfect bus for your next adventure!",
      "Whether you need transport for a school trip, corporate event, or a special occasion, we have the right vehicle to meet your needs.",
      "Contact us today to book your bus."
    ],
    "image": {
      "src": "/assets/img/bus-stop.jpg",
      "alt": "Replace this"
    },
    "buttons": {
      "primary": {
        "link": "/contact#enquiry",
        "text": "Book now"
      },
      "secondary": {
        "link": "/services",
        "text": "Our services"
      }
    }
  }
}
